{
    "@xmlns:dc": "http://purl.org/dc/elements/1.1/",
    "dc:title": "THE GEOCHEMICAL COMPOSITION OF ULTRAMAFIC ROCKS AND ITS RELATION TO THEIR CONTAINED MINERAL DEPOSITS (ABSTRACT).",
    "dc:creator": "SIDDELEY G",
    "dc:date": "1969",
    "dc:type": "Miscellaneous",
    "dc:language": "English",
    "dc:format": "GEOL. SURV. CANADA, PAPER; CAN; 1969, P. 46 A 47",
    "dc:subject": [
        {
            "@xml:lang": "fr",
            "#text": "NI"
        },
        {
            "@xml:lang": "fr",
            "#text": "CR"
        },
        {
            "@xml:lang": "fr",
            "#text": "CU"
        },
        {
            "@xml:lang": "fr",
            "#text": "S"
        },
        {
            "@xml:lang": "fr",
            "#text": "ZIRCONIUM"
        },
        {
            "@xml:lang": "fr",
            "#text": "ULTRABASITE"
        },
        {
            "@xml:lang": "fr",
            "#text": "GEOCHIMIE"
        },
        {
            "@xml:lang": "fr",
            "#text": "GEOLOGIE"
        },
        {
            "@xml:lang": "fr",
            "#text": "SCIENCES DE LA TERRE"
        },
        {
            "@xml:lang": "fr",
            "#text": "ROCHE IGNEE"
        },
        {
            "@xml:lang": "en",
            "#text": "NI"
        },
        {
            "@xml:lang": "en",
            "#text": "CR"
        },
        {
            "@xml:lang": "en",
            "#text": "CU"
        },
        {
            "@xml:lang": "en",
            "#text": "S"
        },
        {
            "@xml:lang": "en",
            "#text": "ZR"
        },
        {
            "@xml:lang": "en",
            "#text": "ULTRABASIC ROCK"
        },
        {
            "@xml:lang": "en",
            "#text": "GEOCHEMISTRY"
        },
        {
            "@xml:lang": "en",
            "#text": "GEOLOGY"
        },
        {
            "@xml:lang": "en",
            "#text": "EARTH SCIENCES"
        },
        "001E01: Sciences de la terre / Earth sciences"
    ],
    "dc:rights": [
        "Inist-CNRS",
        "Sauf mention contraire ci-dessus, le contenu de cette notice bibliographique peut être utilisé dans le cadre d’une licence CC BY 4.0 Inist-CNRS / Unless otherwise stated above, the content of this bibliographic record may be used under a CC BY 4.0 licence by Inist-CNRS / A menos que se haya señalado antes, el contenido de este registro bibliográfico puede ser utilizado al amparo de una licencia CC BY 4.0 Inist-CNRS"
    ],
    "dc:identifier": "Inist-CNRS record number GEODEBRGM6904026591"
}