{
    "@xmlns:dc": "http://purl.org/dc/elements/1.1/",
    "dc:title": "DEPOSITION OF IMMUNOREACTANTS IN PRESERVED HUMAN KIDNEYS.",
    "dc:creator": [
        "GILBOA N",
        "DURANTE D",
        "YOKOTA K",
        "WEIL R III",
        "MCINTOSH RM"
    ],
    "dc:date": "1977",
    "dc:type": "Article",
    "dc:language": "English",
    "dc:format": "TRANSPLANTATION; U.S.A.; DA. 1977; VOL. 24; NO 4; PP. 304-307; BIBL. 17 REF.",
    "dc:subject": [
        {
            "@xml:lang": "fr",
            "#text": "REIN"
        },
        {
            "@xml:lang": "fr",
            "#text": "CONSERVATION"
        },
        {
            "@xml:lang": "fr",
            "#text": "HYPOTHERMIE PROVOQUEE"
        },
        {
            "@xml:lang": "fr",
            "#text": "IMMUNOGLOBULINE"
        },
        {
            "@xml:lang": "fr",
            "#text": "COMPLEMENT C3"
        },
        {
            "@xml:lang": "fr",
            "#text": "FIBRINOGENE"
        },
        {
            "@xml:lang": "fr",
            "#text": "HOMME"
        },
        {
            "@xml:lang": "fr",
            "#text": "IMMUNOFLUORESCENCE"
        },
        {
            "@xml:lang": "fr",
            "#text": "IMMUNOHISTOCHIMIE"
        },
        {
            "@xml:lang": "fr",
            "#text": "PREPARATION"
        },
        {
            "@xml:lang": "fr",
            "#text": "GREFFON"
        },
        {
            "@xml:lang": "fr",
            "#text": "HOMOTRANSPLANTATION"
        },
        {
            "@xml:lang": "fr",
            "#text": "IMMUNOLOGIE"
        },
        {
            "@xml:lang": "en",
            "#text": "KIDNEY"
        },
        {
            "@xml:lang": "en",
            "#text": "INDUCED HYPOTHERMIA"
        },
        {
            "@xml:lang": "en",
            "#text": "IMMUNOGLOBULINS"
        },
        {
            "@xml:lang": "en",
            "#text": "COMPLEMENT C3"
        },
        {
            "@xml:lang": "en",
            "#text": "FIBRINOGEN"
        },
        {
            "@xml:lang": "en",
            "#text": "HUMAN"
        },
        {
            "@xml:lang": "en",
            "#text": "IMMUNOFLUORESCENCE"
        },
        {
            "@xml:lang": "en",
            "#text": "IMMUNOHISTOCHEMISTRY"
        },
        {
            "@xml:lang": "en",
            "#text": "PREPARATION"
        },
        {
            "@xml:lang": "en",
            "#text": "HOMOTRANSPLANTATION"
        },
        {
            "@xml:lang": "en",
            "#text": "IMMUNOLOGY"
        },
        "002B05: Pathologie infectieuse / Infectious diseases"
    ],
    "dc:rights": [
        "Inist-CNRS",
        "Sauf mention contraire ci-dessus, le contenu de cette notice bibliographique peut être utilisé dans le cadre d’une licence CC BY 4.0 Inist-CNRS / Unless otherwise stated above, the content of this bibliographic record may be used under a CC BY 4.0 licence by Inist-CNRS / A menos que se haya señalado antes, el contenido de este registro bibliográfico puede ser utilizado al amparo de una licencia CC BY 4.0 Inist-CNRS"
    ],
    "dc:identifier": "Inist-CNRS record number PASCAL7850194952"
}