{
    "@xmlns:dc": "http://purl.org/dc/elements/1.1/",
    "dc:title": "LIGHT QUALITY AND THE PRIMARY ENERGY STORING PROCESSES OF PHOTOSYNTHESIS",
    "dc:creator": [
        "DEMIDOV ED",
        "BELL LN"
    ],
    "dc:date": "1978",
    "dc:type": "Article",
    "dc:language": "English",
    "dc:format": "PHOTOSYNTHETICA; CSK; DA. 1978; VOL. 12; NO 2; PP. 158-165; BIBL. 18 REF.",
    "dc:subject": [
        {
            "@xml:lang": "fr",
            "#text": "DICOTYLEDONES"
        },
        {
            "@xml:lang": "fr",
            "#text": "ALGAE"
        },
        {
            "@xml:lang": "fr",
            "#text": "CHLOROPHYCOPHYTA"
        },
        {
            "@xml:lang": "fr",
            "#text": "PHOTOSYNTHESE"
        },
        {
            "@xml:lang": "fr",
            "#text": "FACTEUR PHOTIQUE"
        },
        {
            "@xml:lang": "fr",
            "#text": "PISUM"
        },
        {
            "@xml:lang": "fr",
            "#text": "BIOLOGIE VEGETALE"
        },
        {
            "@xml:lang": "en",
            "#text": "DICOTYLEDONES"
        },
        {
            "@xml:lang": "en",
            "#text": "DICOTYLEDONEAE"
        },
        {
            "@xml:lang": "en",
            "#text": "ALGAE"
        },
        {
            "@xml:lang": "en",
            "#text": "CHLOROPHYCOPHYTA"
        },
        {
            "@xml:lang": "en",
            "#text": "CHLOROPHYTA"
        },
        {
            "@xml:lang": "en",
            "#text": "PHOTOSYNTHESIS"
        },
        {
            "@xml:lang": "en",
            "#text": "LIGHT EFFECT"
        },
        {
            "@xml:lang": "en",
            "#text": "PISUM"
        },
        {
            "@xml:lang": "en",
            "#text": "PLANT BIOLOGY"
        },
        "002A10: Physiologie vegetale et developpement / Plant physiology and development"
    ],
    "dc:rights": [
        "Inist-CNRS",
        "Sauf mention contraire ci-dessus, le contenu de cette notice bibliographique peut être utilisé dans le cadre d’une licence CC BY 4.0 Inist-CNRS / Unless otherwise stated above, the content of this bibliographic record may be used under a CC BY 4.0 licence by Inist-CNRS / A menos que se haya señalado antes, el contenido de este registro bibliográfico puede ser utilizado al amparo de una licencia CC BY 4.0 Inist-CNRS"
    ],
    "dc:identifier": "Inist-CNRS record number PASCAL7910213363"
}