{
    "@xmlns:dc": "http://purl.org/dc/elements/1.1/",
    "dc:title": "NUMERICAL INVERSION OF THE V-V MASTER EQUATION",
    "dc:creator": "WASSAM WA JR",
    "dc:date": "1979",
    "dc:type": "Article",
    "dc:language": "English",
    "dc:format": "CHEM. PHYS. LETTERS; NLD; DA. 1979; VOL. 60; NO 2; PP. 220-223; BIBL. 6 REF.",
    "dc:subject": [
        {
            "@xml:lang": "fr",
            "#text": "CARBONE COMPOSE"
        },
        {
            "@xml:lang": "fr",
            "#text": "OXYDE"
        },
        {
            "@xml:lang": "fr",
            "#text": "ETAT VIBRATIONNEL EXCITE"
        },
        {
            "@xml:lang": "fr",
            "#text": "TRANSFERT ENERGIE EXCITATION"
        },
        {
            "@xml:lang": "fr",
            "#text": "TRANSFERT ENERGIE VIBRATIONNEL VIBRATIONNEL"
        },
        {
            "@xml:lang": "fr",
            "#text": "COLLISION MOLECULE MOLECULE"
        },
        {
            "@xml:lang": "fr",
            "#text": "PROBLEME INVERSE"
        },
        {
            "@xml:lang": "fr",
            "#text": "ETUDE THEORIQUE"
        },
        {
            "@xml:lang": "fr",
            "#text": "EQUATION MAITRESSE"
        },
        {
            "@xml:lang": "fr",
            "#text": "THEORIE INFORMATION"
        },
        {
            "@xml:lang": "fr",
            "#text": "CARBONE MONOXYDE"
        },
        {
            "@xml:lang": "fr",
            "#text": "COMPOSE MINERAL"
        },
        {
            "@xml:lang": "fr",
            "#text": "MOLECULE DIATOMIQUE"
        },
        {
            "@xml:lang": "fr",
            "#text": "PHYSIQUE MOLECULAIRE"
        },
        {
            "@xml:lang": "fr",
            "#text": "PHYSIQUE ATOMIQUE"
        },
        {
            "@xml:lang": "en",
            "#text": "CARBON COMPOUND"
        },
        {
            "@xml:lang": "en",
            "#text": "OXIDES"
        },
        {
            "@xml:lang": "en",
            "#text": "VIBRATIONALLY EXCITED STATE"
        },
        {
            "@xml:lang": "en",
            "#text": "EXCITATION ENERGY TRANSFER"
        },
        {
            "@xml:lang": "en",
            "#text": "VIBRATIONAL VIBRATIONAL ENERGY TRANSFER"
        },
        {
            "@xml:lang": "en",
            "#text": "MOLECULE MOLECULE COLLISION"
        },
        {
            "@xml:lang": "en",
            "#text": "INVERSE PROBLEM"
        },
        {
            "@xml:lang": "en",
            "#text": "THEORETICAL STUDY"
        },
        {
            "@xml:lang": "en",
            "#text": "MASTER EQUATION"
        },
        {
            "@xml:lang": "en",
            "#text": "INFORMATION THEORY"
        },
        {
            "@xml:lang": "en",
            "#text": "CARBON MONOXIDE"
        },
        {
            "@xml:lang": "en",
            "#text": "INORGANIC COMPOUND"
        },
        {
            "@xml:lang": "en",
            "#text": "DIATOMIC MOLECULE"
        },
        {
            "@xml:lang": "en",
            "#text": "MOLECULAR PHYSICS"
        },
        {
            "@xml:lang": "en",
            "#text": "ATOMIC PHYSICS"
        },
        "001B30: Physique atomique et moleculaire / Atomic and molecular physics"
    ],
    "dc:rights": [
        "Inist-CNRS",
        "Sauf mention contraire ci-dessus, le contenu de cette notice bibliographique peut être utilisé dans le cadre d’une licence CC BY 4.0 Inist-CNRS / Unless otherwise stated above, the content of this bibliographic record may be used under a CC BY 4.0 licence by Inist-CNRS / A menos que se haya señalado antes, el contenido de este registro bibliográfico puede ser utilizado al amparo de una licencia CC BY 4.0 Inist-CNRS"
    ],
    "dc:identifier": "Inist-CNRS record number PASCAL7940270872"
}