{
    "@xmlns:dc": "http://purl.org/dc/elements/1.1/",
    "dc:title": "Das Reich und die Kraft: Geistestaufe in pfingstlerischer und ökumenischer Perspektive",
    "dc:creator": "MACCHIA, Frank D",
    "dc:relation": "Evangelische Theologie -- Evang. Theol, ISSN 0014-3502, Vol. 69 (4) , pp. 286-299",
    "dc:date": "2009",
    "dc:type": [
        "Text",
        "Article"
    ],
    "dc:language": "German",
    "dc:publisher": "Gütersloher Verlagshaus",
    "dc:format": [
        "print",
        "14 p."
    ],
    "dc:subject": [
        {
            "@xml:lang": "fr",
            "#text": "Baptême dans l'Esprit"
        },
        {
            "@xml:lang": "fr",
            "#text": "Oecuménisme"
        },
        {
            "@xml:lang": "fr",
            "#text": "Pentecôtisme"
        },
        {
            "@xml:lang": "fr",
            "#text": "Pneumatologie"
        },
        {
            "@xml:lang": "fr",
            "#text": "Renouveau charismatique"
        },
        {
            "@xml:lang": "fr",
            "#text": "Rite d'initiation"
        },
        {
            "@xml:lang": "fr",
            "#text": "Sacrement"
        },
        {
            "@xml:lang": "en",
            "#text": "Spirit baptism"
        },
        {
            "@xml:lang": "en",
            "#text": "Oecumenism"
        },
        {
            "@xml:lang": "en",
            "#text": "Pentecostalism"
        },
        {
            "@xml:lang": "en",
            "#text": "Pneumatology"
        },
        {
            "@xml:lang": "en",
            "#text": "Charismatic Revival"
        },
        {
            "@xml:lang": "en",
            "#text": "Initiation rite"
        },
        {
            "@xml:lang": "en",
            "#text": "Sacrament"
        },
        "527-: Histoire et sciences des religions / History and sciences of religions",
        "527-865: Christianisme / Christianity",
        "527-1345: Baptême / Baptism"
    ],
    "dc:rights": [
        "Inist-CNRS",
        "Sauf mention contraire ci-dessus, le contenu de cette notice bibliographique peut être utilisé dans le cadre d’une licence CC BY 4.0 Inist-CNRS / Unless otherwise stated above, the content of this bibliographic record may be used under a CC BY 4.0 licence by Inist-CNRS / A menos que se haya señalado antes, el contenido de este registro bibliográfico puede ser utilizado al amparo de una licencia CC BY 4.0 Inist-CNRS"
    ],
    "dc:identifier": "Inist-CNRS record number 21839798"
}