{
    "@xmlns:dc": "http://purl.org/dc/elements/1.1/",
    "dc:title": "El tiempo y los objetos",
    "dc:creator": "SCHULTZ, M",
    "dc:relation": "Revista de Filosofia Santiago de Chile, Vol. 21-22, pp. 107-113",
    "dc:date": "1983",
    "dc:type": [
        "Text",
        "Article"
    ],
    "dc:language": "Spanish, Castilian",
    "dc:format": "print",
    "dc:subject": "519-2: Philosophie Générale. Métaphysique / General philosophy. Metaphysics",
    "dc:rights": [
        "Inist-CNRS",
        "Sauf mention contraire ci-dessus, le contenu de cette notice bibliographique peut être utilisé dans le cadre d’une licence CC BY 4.0 Inist-CNRS / Unless otherwise stated above, the content of this bibliographic record may be used under a CC BY 4.0 licence by Inist-CNRS / A menos que se haya señalado antes, el contenido de este registro bibliográfico puede ser utilizado al amparo de una licencia CC BY 4.0 Inist-CNRS"
    ],
    "dc:identifier": "Inist-CNRS record number 12203800"
}